scoremipsum/__init__.py
scoremipsum/data.py
scoremipsum/demo.py
scoremipsum/generation.py
scoremipsum/ops.py
scoremipsum/schedule.py
scoremipsum/score.py
scoremipsum/util/__init__.py
scoremipsum/util/conversion.py
scoremipsum/util/scheduler.py
scoremipsum/util/support.py
scoremipsum/util/team.py
scoremipsum-0.0.9.dist-info/entry_points.txt
scoremipsum-0.0.9.dist-info/licenses/LICENSE
scoremipsum-0.0.9.dist-info/WHEEL
scoremipsum-0.0.9.dist-info/METADATA
scoremipsum-0.0.9.dist-info/RECORD
