Metadata-Version: 2.4
Name: scoremipsum
Version: 0.0.9
Summary: SCOREM - generate sportsball score data for testing and demos (aka scoremipsum)
Keywords: scoremipsum,score,sports,sportsball,generation
Author-email: Chuck Staples <cjstaples@gmail.com>
Maintainer-email: Charles Staples <cjstaples@weaselwatch.com>, Jason Staples <js.saberx@gmail.com>
Requires-Python: >=3.9
License-Expression: MIT
License-File: LICENSE
Project-URL: Home, https://github.com/cjstaples/scorem-ipsum
Project-URL: Issues, https://github.com/cjstaples/scorem-ipsum/issues
